Metadata-Version: 2.1
Name: scrape-google-results
Version: 1.0.0
Summary: A python library to scrape google search result
Home-page: UNKNOWN
Author: DataKund
Author-email: datakund@gmail.com
License: Apache License 2.0
Keywords: google python bot_studio automation search result scraper title description
Platform: UNKNOWN
License-File: LICENSE
